{
  "</s>": 2,
  "<pad>": 0,
  "<s>": 1,
  "<unk>": 3,
  "a": 4,
  "ai": 5,
  "an": 6,
  "ang": 7,
  "ao": 8,
  "b": 9,
  "c": 10,
  "ch": 11,
  "d": 12,
  "e": 13,
  "ei": 14,
  "en": 15,
  "eng": 16,
  "er": 17,
  "f": 18,
  "g": 19,
  "h": 20,
  "i": 21,
  "ia": 22,
  "ian": 23,
  "iang": 24,
  "iao": 25,
  "ie": 26,
  "in": 27,
  "ing": 28,
  "iong": 29,
  "iu": 30,
  "ix": 31,
  "iy": 32,
  "iz": 33,
  "j": 34,
  "k": 35,
  "l": 36,
  "m": 37,
  "n": 38,
  "o": 39,
  "ong": 40,
  "ou": 41,
  "p": 42,
  "q": 43,
  "r": 44,
  "s": 45,
  "sh": 46,
  "sil": 47,
  "t": 48,
  "u": 49,
  "ua": 50,
  "uai": 51,
  "uan": 52,
  "uang": 53,
  "ueng": 54,
  "ui": 55,
  "un": 56,
  "uo": 57,
  "v": 58,
  "van": 59,
  "ve": 60,
  "vn": 61,
  "x": 62,
  "z": 63,
  "zh": 64
}
